HW2/Struc/count.v

module DTFF_reset(output Q, Q_not, input D, clk, reset);
    wire    wl0, wl1, wl2, wl3;

    nand    g0 (wl0, wl1, wl3),
            g1 (wl1, clk, wl0, reset),
            g2 (wl2, clk, wl1, wl3),
            g3 (wl3, D, wl2, reset),
            g4 (Q, wl1, Q_not),
            g5 (Q_not, wl2, Q, reset);
endmodule


module JK_FF_reset(output Q, input J, K, clk, reset);
    wire    K_not, qnot, wl0, wl1, wl2;

    // instantiate gates
    not     g0 (K_not, K);

    and     g1 (wl0, J, qnot),
            g2 (wl1, K_not, Q);

    or      g3 (wl2, wl0, wl1);
    // instantiate D-Flip-flop module
    DTFF_reset D0 (q, qnot, wl2, clk, reset);
endmodule

module JKFF(Q,q,J,K,clk);//jkflip-flop
input J,K,clk;
output Q,q;
//wire w_s,w_r,wQ,wq;
//assign wQ=Q;
//assign wq=q;
assign q=~Q;
JK_FF_reset r(.Q(Q),.J(J),.K(K),.clk(clk),.reset(1'b0));
//nand  n1(w_s,J,wq,clk);
//nand  n2(w_r,K,wQ,clk);
//nand  ns(Q,wq,w_s);
//nand  nr(wq,wQ,w_r);
endmodule

module MUX(O,A,B,S);
input A,B,S;
output O;

wire w0,w1,w2;
not n1(w0,S);
and a1(w1,A,w0);
and a2(w2,B,S);
or o1(O,w1,w2);
endmodule

module counter(count,clk,updown,rst);//5b updown

input clk,updown,rst;
output [4:0]count;
wire ud_,nrst;
wire w0,w1,w2,w3,w4,w5,w6,w7,w8,w9,w10,w11,w12,w13,w14,w15,w16,w17,w18,w19,w20,w21;


JKFF jk0(.Q(count[0]),.q(q0),.J(w20),.K(w21),.clk(clk));
JKFF jk1(.Q(count[1]),.q(q1),.J(w16),.K(w12),.clk(clk));
JKFF jk2(.Q(count[2]),.q(q2),.J(w17),.K(w13),.clk(clk));
JKFF jk3(.Q(count[3]),.q(q3),.J(w18),.K(w14),.clk(clk));
JKFF jk4(.Q(count[4]),.q(q4),.J(w19),.K(w15),.clk(clk));

not updown_(ud_,updown);
and Q_0(w0,q0,ud_);
and Q_1(w1,w0,q1);
and Q_2(w2,w1,q2);
and Q_3(w3,w2,q3);

and Q0(w4,count[0],updown);
and Q1(w5,count[1],w4);
and Q2(w6,count[2],w5);
and Q3(w7,count[3],w6);

or o0(w8,w0,w4);
or o1(w9,w1,w5);
or o2(w10,w2,w6);
or o3(w11,w3,w7);

not reset_(nrst,rst);



MUX m0k(w12,w8,rst,rst);
MUX m1k(w13,w9,rst,rst);
MUX m2k(w14,w10,rst,rst);
MUX m3k(w15,w11,rst,rst);

MUX m0j(w16,w8,nrst,rst);
MUX m1j(w17,w9,nrst,rst);
MUX m2j(w18,w10,nrst,rst);
MUX m3j(w19,w11,nrst,rst);

MUX msj(w20,nrst,nrst,rst);
MUX msk(w21,nrst,rst,rst);
endmodule

HW2/Struc/testbench.v
`timescale 1ns/10ps

`include        "count.v"

module count_tb();
reg clk, rst,updown;
wire [4:0] count;

counter dut(.clk(clk), .rst(rst),.updown(updown), .count(count));
initial begin 
clk=0;
forever #5 clk=~clk;
end
initial begin
rst=1;
updown=0;
#20;
rst=0;
#50;
updown=1;
# 80;
updown=0;
#160;
rst=1;
$finish;
end
initial
begin
	$dumpfile("count.vcd");
	$dumpvars;
end
endmodule

HW2/Struc/count.vcd
$date
    Oct 16, 2019  00:18:09
$end
$version
    TOOL:	ncsim	15.20-s039
$end
$timescale
    10 ps
$end

$scope module count_tb $end
$var reg       1 !    clk  $end
$var reg       1 "    rst  $end
$var reg       1 #    updown  $end
$var wire      1 $    count [4] $end
$var wire      1 %    count [3] $end
$var wire      1 &    count [2] $end
$var wire      1 '    count [1] $end
$var wire      1 (    count [0] $end

$scope module dut $end
$var wire      1 )    clk  $end
$var wire      1 *    updown  $end
$var wire      1 +    rst  $end
$var wire      1 $    count [4] $end
$var wire      1 %    count [3] $end
$var wire      1 &    count [2] $end
$var wire      1 '    count [1] $end
$var wire      1 (    count [0] $end
$var wire      1 ,    ud_  $end
$var wire      1 -    nrst  $end
$var wire      1 .    w0  $end
$var wire      1 /    w1  $end
$var wire      1 0    w2  $end
$var wire      1 1    w3  $end
$var wire      1 2    w4  $end
$var wire      1 3    w5  $end
$var wire      1 4    w6  $end
$var wire      1 5    w7  $end
$var wire      1 6    w8  $end
$var wire      1 7    w9  $end
$var wire      1 8    w10  $end
$var wire      1 9    w11  $end
$var wire      1 :    w12  $end
$var wire      1 ;    w13  $end
$var wire      1 <    w14  $end
$var wire      1 =    w15  $end
$var wire      1 >    w16  $end
$var wire      1 ?    w17  $end
$var wire      1 @    w18  $end
$var wire      1 A    w19  $end
$var wire      1 B    w20  $end
$var wire      1 C    w21  $end
$var wire      1 D    q0  $end
$var wire      1 E    q1  $end
$var wire      1 F    q2  $end
$var wire      1 G    q3  $end
$var wire      1 H    q4  $end

$scope module jk0 $end
$var wire      1 B    J  $end
$var wire      1 C    K  $end
$var wire      1 )    clk  $end
$var wire      1 (    Q  $end
$var wire      1 D    q  $end

$scope module r $end
$var wire      1 (    Q  $end
$var wire      1 B    J  $end
$var wire      1 C    K  $end
$var wire      1 )    clk  $end
$var wire      1 I    reset  $end
$var wire      1 J    K_not  $end
$var wire      1 K    qnot  $end
$var wire      1 L    wl0  $end
$var wire      1 M    wl1  $end
$var wire      1 N    wl2  $end
$var wire      1 O    q  $end

$scope module D0 $end
$var wire      1 O    Q  $end
$var wire      1 K    Q_not  $end
$var wire      1 N    D  $end
$var wire      1 )    clk  $end
$var wire      1 I    reset  $end
$var wire      1 P    wl0  $end
$var wire      1 Q    wl1  $end
$var wire      1 R    wl2  $end
$var wire      1 S    wl3  $end
$upscope $end

$upscope $end

$upscope $end


$scope module jk1 $end
$var wire      1 >    J  $end
$var wire      1 :    K  $end
$var wire      1 )    clk  $end
$var wire      1 '    Q  $end
$var wire      1 E    q  $end

$scope module r $end
$var wire      1 '    Q  $end
$var wire      1 >    J  $end
$var wire      1 :    K  $end
$var wire      1 )    clk  $end
$var wire      1 T    reset  $end
$var wire      1 U    K_not  $end
$var wire      1 V    qnot  $end
$var wire      1 W    wl0  $end
$var wire      1 X    wl1  $end
$var wire      1 Y    wl2  $end
$var wire      1 Z    q  $end

$scope module D0 $end
$var wire      1 Z    Q  $end
$var wire      1 V    Q_not  $end
$var wire      1 Y    D  $end
$var wire      1 )    clk  $end
$var wire      1 T    reset  $end
$var wire      1 [    wl0  $end
$var wire      1 \    wl1  $end
$var wire      1 ]    wl2  $end
$var wire      1 ^    wl3  $end
$upscope $end

$upscope $end

$upscope $end


$scope module jk2 $end
$var wire      1 ?    J  $end
$var wire      1 ;    K  $end
$var wire      1 )    clk  $end
$var wire      1 &    Q  $end
$var wire      1 F    q  $end

$scope module r $end
$var wire      1 &    Q  $end
$var wire      1 ?    J  $end
$var wire      1 ;    K  $end
$var wire      1 )    clk  $end
$var wire      1 _    reset  $end
$var wire      1 `    K_not  $end
$var wire      1 a    qnot  $end
$var wire      1 b    wl0  $end
$var wire      1 c    wl1  $end
$var wire      1 d    wl2  $end
$var wire      1 e    q  $end

$scope module D0 $end
$var wire      1 e    Q  $end
$var wire      1 a    Q_not  $end
$var wire      1 d    D  $end
$var wire      1 )    clk  $end
$var wire      1 _    reset  $end
$var wire      1 f    wl0  $end
$var wire      1 g    wl1  $end
$var wire      1 h    wl2  $end
$var wire      1 i    wl3  $end
$upscope $end

$upscope $end

$upscope $end


$scope module jk3 $end
$var wire      1 @    J  $end
$var wire      1 <    K  $end
$var wire      1 )    clk  $end
$var wire      1 %    Q  $end
$var wire      1 G    q  $end

$scope module r $end
$var wire      1 %    Q  $end
$var wire      1 @    J  $end
$var wire      1 <    K  $end
$var wire      1 )    clk  $end
$var wire      1 j    reset  $end
$var wire      1 k    K_not  $end
$var wire      1 l    qnot  $end
$var wire      1 m    wl0  $end
$var wire      1 n    wl1  $end
$var wire      1 o    wl2  $end
$var wire      1 p    q  $end

$scope module D0 $end
$var wire      1 p    Q  $end
$var wire      1 l    Q_not  $end
$var wire      1 o    D  $end
$var wire      1 )    clk  $end
$var wire      1 j    reset  $end
$var wire      1 q    wl0  $end
$var wire      1 r    wl1  $end
$var wire      1 s    wl2  $end
$var wire      1 t    wl3  $end
$upscope $end

$upscope $end

$upscope $end


$scope module jk4 $end
$var wire      1 A    J  $end
$var wire      1 =    K  $end
$var wire      1 )    clk  $end
$var wire      1 $    Q  $end
$var wire      1 H    q  $end

$scope module r $end
$var wire      1 $    Q  $end
$var wire      1 A    J  $end
$var wire      1 =    K  $end
$var wire      1 )    clk  $end
$var wire      1 u    reset  $end
$var wire      1 v    K_not  $end
$var wire      1 w    qnot  $end
$var wire      1 x    wl0  $end
$var wire      1 y    wl1  $end
$var wire      1 z    wl2  $end
$var wire      1 {    q  $end

$scope module D0 $end
$var wire      1 {    Q  $end
$var wire      1 w    Q_not  $end
$var wire      1 z    D  $end
$var wire      1 )    clk  $end
$var wire      1 u    reset  $end
$var wire      1 |    wl0  $end
$var wire      1 }    wl1  $end
$var wire      1 ~    wl2  $end
$var wire      1 !!   wl3  $end
$upscope $end

$upscope $end

$upscope $end


$scope module m0k $end
$var wire      1 6    A  $end
$var wire      1 +    B  $end
$var wire      1 +    S  $end
$var wire      1 :    O  $end
$var wire      1 "!   w0  $end
$var wire      1 #!   w1  $end
$var wire      1 $!   w2  $end
$upscope $end


$scope module m1k $end
$var wire      1 7    A  $end
$var wire      1 +    B  $end
$var wire      1 +    S  $end
$var wire      1 ;    O  $end
$var wire      1 %!   w0  $end
$var wire      1 &!   w1  $end
$var wire      1 '!   w2  $end
$upscope $end


$scope module m2k $end
$var wire      1 8    A  $end
$var wire      1 +    B  $end
$var wire      1 +    S  $end
$var wire      1 <    O  $end
$var wire      1 (!   w0  $end
$var wire      1 )!   w1  $end
$var wire      1 *!   w2  $end
$upscope $end


$scope module m3k $end
$var wire      1 9    A  $end
$var wire      1 +    B  $end
$var wire      1 +    S  $end
$var wire      1 =    O  $end
$var wire      1 +!   w0  $end
$var wire      1 ,!   w1  $end
$var wire      1 -!   w2  $end
$upscope $end


$scope module m0j $end
$var wire      1 6    A  $end
$var wire      1 -    B  $end
$var wire      1 +    S  $end
$var wire      1 >    O  $end
$var wire      1 .!   w0  $end
$var wire      1 /!   w1  $end
$var wire      1 0!   w2  $end
$upscope $end


$scope module m1j $end
$var wire      1 7    A  $end
$var wire      1 -    B  $end
$var wire      1 +    S  $end
$var wire      1 ?    O  $end
$var wire      1 1!   w0  $end
$var wire      1 2!   w1  $end
$var wire      1 3!   w2  $end
$upscope $end


$scope module m2j $end
$var wire      1 8    A  $end
$var wire      1 -    B  $end
$var wire      1 +    S  $end
$var wire      1 @    O  $end
$var wire      1 4!   w0  $end
$var wire      1 5!   w1  $end
$var wire      1 6!   w2  $end
$upscope $end


$scope module m3j $end
$var wire      1 9    A  $end
$var wire      1 -    B  $end
$var wire      1 +    S  $end
$var wire      1 A    O  $end
$var wire      1 7!   w0  $end
$var wire      1 8!   w1  $end
$var wire      1 9!   w2  $end
$upscope $end


$scope module msj $end
$var wire      1 -    A  $end
$var wire      1 -    B  $end
$var wire      1 +    S  $end
$var wire      1 B    O  $end
$var wire      1 :!   w0  $end
$var wire      1 ;!   w1  $end
$var wire      1 <!   w2  $end
$upscope $end


$scope module msk $end
$var wire      1 -    A  $end
$var wire      1 +    B  $end
$var wire      1 +    S  $end
$var wire      1 C    O  $end
$var wire      1 =!   w0  $end
$var wire      1 >!   w1  $end
$var wire      1 ?!   w2  $end
$upscope $end

$upscope $end

$upscope $end

$enddefinitions $end
$dumpvars
0!
1"
0#
z$
z%
z&
z'
z(
0)
0*
1+
1,
0-
x.
x/
x0
x1
02
03
04
05
x6
x7
x8
x9
1:
1;
1<
1=
0>
0?
0@
0A
0B
1C
xD
xE
xF
xG
xH
0I
0J
1K
0L
0M
0N
0O
0P
1Q
1R
1S
0T
0U
1V
0W
0X
0Y
0Z
0[
1\
1]
1^
0_
0`
1a
0b
0c
0d
0e
0f
1g
1h
1i
0j
0k
1l
0m
0n
0o
0p
0q
1r
1s
1t
0u
0v
1w
0x
0y
0z
0{
0|
1}
1~
1!!
0"!
0#!
1$!
0%!
0&!
1'!
0(!
0)!
1*!
0+!
0,!
1-!
0.!
0/!
00!
01!
02!
03!
04!
05!
06!
07!
08!
09!
0:!
0;!
0<!
0=!
0>!
1?!
$end
#500
1!
1)
0~
0s
0h
0]
0R
#1000
0!
0)
1~
1s
1h
1]
1R
#1500
1!
1)
0~
0s
0h
0]
0R
#2000
0"
0!
0)
0+
1-
1=!
0?!
1>!
1:!
1;!
1B
17!
x8!
xA
14!
x5!
x@
11!
x2!
x?
1.!
x/!
x>
1+!
0-!
x,!
x=
1(!
0*!
x)!
x<
1%!
0'!
x&!
x;
1"!
0$!
x#!
x:
1~
1s
1h
1]
1R
xU
xX
xW
xY
x`
xc
xb
xd
xk
xn
xm
xo
xv
xy
xx
xz
1L
1N
#2500
1!
1)
0~
0s
0h
0]
0R
#3000
0!
0)
1~
1s
1h
1]
1R
#3500
1!
1)
0~
0s
0h
0]
0R
#4000
0!
0)
1~
1s
1h
1]
1R
#4500
1!
1)
0~
0s
0h
0]
0R
#5000
0!
0)
1~
1s
1h
1]
1R
#5500
1!
1)
0~
0s
0h
0]
0R
#6000
0!
0)
1~
1s
1h
1]
1R
#6500
1!
1)
0~
0s
0h
0]
0R
#7000
1#
0!
0)
1*
x2
0,
0.
1~
1s
1h
1]
1R
0/
x3
x4
00
x5
01
#7500
1!
1)
0~
0s
0h
0]
0R
#8000
0!
0)
1~
1s
1h
1]
1R
#8500
1!
1)
0~
0s
0h
0]
0R
#9000
0!
0)
1~
1s
1h
1]
1R
#9500
1!
1)
0~
0s
0h
0]
0R
#10000
0!
0)
1~
1s
1h
1]
1R
#10500
1!
1)
0~
0s
0h
0]
0R
#11000
0!
0)
1~
1s
1h
1]
1R
#11500
1!
1)
0~
0s
0h
0]
0R
#12000
0!
0)
1~
1s
1h
1]
1R
#12500
1!
1)
0~
0s
0h
0]
0R
#13000
0!
0)
1~
1s
1h
1]
1R
#13500
1!
1)
0~
0s
0h
0]
0R
#14000
0!
0)
1~
1s
1h
1]
1R
#14500
1!
1)
0~
0s
0h
0]
0R
#15000
0#
0!
0)
0*
02
1,
x.
1~
1s
1h
1]
1R
x/
03
04
x0
05
x1
#15500
1!
1)
0~
0s
0h
0]
0R
#16000
0!
0)
1~
1s
1h
1]
1R
#16500
1!
1)
0~
0s
0h
0]
0R
#17000
0!
0)
1~
1s
1h
1]
1R
#17500
1!
1)
0~
0s
0h
0]
0R
#18000
0!
0)
1~
1s
1h
1]
1R
#18500
1!
1)
0~
0s
0h
0]
0R
#19000
0!
0)
1~
1s
1h
1]
1R
#19500
1!
1)
0~
0s
0h
0]
0R
#20000
0!
0)
1~
1s
1h
1]
1R
#20500
1!
1)
0~
0s
0h
0]
0R
#21000
0!
0)
1~
1s
1h
1]
1R
#21500
1!
1)
0~
0s
0h
0]
0R
#22000
0!
0)
1~
1s
1h
1]
1R
#22500
1!
1)
0~
0s
0h
0]
0R
#23000
0!
0)
1~
1s
1h
1]
1R
#23500
1!
1)
0~
0s
0h
0]
0R
#24000
0!
0)
1~
1s
1h
1]
1R
#24500
1!
1)
0~
0s
0h
0]
0R
#25000
0!
0)
1~
1s
1h
1]
1R
#25500
1!
1)
0~
0s
0h
0]
0R
#26000
0!
0)
1~
1s
1h
1]
1R
#26500
1!
1)
0~
0s
0h
0]
0R
#27000
0!
0)
1~
1s
1h
1]
1R
#27500
1!
1)
0~
0s
0h
0]
0R
#28000
0!
0)
1~
1s
1h
1]
1R
#28500
1!
1)
0~
0s
0h
0]
0R
#29000
0!
0)
1~
1s
1h
1]
1R
#29500
1!
1)
0~
0s
0h
0]
0R
#30000
0!
0)
1~
1s
1h
1]
1R
#30500
1!
1)
0~
0s
0h
0]
0R
#31000
1"
