HW2/Behav/count.v


module count(clk,rst,updown,count); //0-20 Counter
output [4:0] count;
input updown;
reg [4:0] count_reg;
input rst,clk;

always @(posedge clk or posedge rst)
begin
if(rst)
 count_reg <= 5'b0;
else if(~updown)
 count_reg <= (count_reg<5'd20)?count_reg + 5'b1:count_reg;
else
 count_reg <= (count_reg>5'b0)?count_reg - 5'b1:count_reg;
end 
assign count = count_reg;
endmodule

HW2/Behav/testbench.v
`timescale 1ns/10ps

`include        "count.v"

module count_tb();
reg clk, rst,updown;
wire [4:0] count;

count dut(.clk(clk), .rst(rst),.updown(updown), .count(count));
initial begin 
clk=0;
forever #1 clk=~clk;
end
initial begin
rst=1;
updown=0;
#20;
rst=0;
#50;
updown=1;
# 80;
updown=0;
#160;
rst=1;
$finish;
end
initial
begin
	$dumpfile("count.vcd");
	$dumpvars;
end
endmodule

HW2/Behavior/count.vcd
$date
    Oct 15, 2019  22:10:14
$end
$version
    TOOL:	ncsim	15.20-s039
$end
$timescale
    10 ps
$end

$scope module count_tb $end
$var reg       1 !    clk  $end
$var reg       1 "    rst  $end
$var reg       1 #    updown  $end
$var wire      5 $    count [4:0] $end

$scope module dut $end
$var wire      5 $    count [4:0] $end
$var wire      1 %    updown  $end
$var reg       5 &    count_reg [4:0] $end
$var wire      1 '    rst  $end
$var wire      1 (    clk  $end
$upscope $end

$upscope $end

$enddefinitions $end
$dumpvars
0!
1"
0#
b0 $
0%
b0 &
1'
0(
$end
#100
1!
1(
#200
0!
0(
#300
1!
1(
#400
0!
0(
#500
1!
1(
#600
0!
0(
#700
1!
1(
#800
0!
0(
#900
1!
1(
#1000
0!
0(
#1100
1!
1(
#1200
0!
0(
#1300
1!
1(
#1400
0!
0(
#1500
1!
1(
#1600
0!
0(
#1700
1!
1(
#1800
0!
0(
#1900
1!
1(
#2000
0"
0!
0(
0'
#2100
1!
1(
b1 &
b1 $
#2200
0!
0(
#2300
1!
1(
b10 &
b10 $
#2400
0!
0(
#2500
1!
1(
b11 &
b11 $
#2600
0!
0(
#2700
1!
1(
b100 &
b100 $
#2800
0!
0(
#2900
1!
1(
b101 &
b101 $
#3000
0!
0(
#3100
1!
1(
b110 &
b110 $
#3200
0!
0(
#3300
1!
1(
b111 &
b111 $
#3400
0!
0(
#3500
1!
1(
b1000 &
b1000 $
#3600
0!
0(
#3700
1!
1(
b1001 &
b1001 $
#3800
0!
0(
#3900
1!
1(
b1010 &
b1010 $
#4000
0!
0(
#4100
1!
1(
b1011 &
b1011 $
#4200
0!
0(
#4300
1!
1(
b1100 &
b1100 $
#4400
0!
0(
#4500
1!
1(
b1101 &
b1101 $
#4600
0!
0(
#4700
1!
1(
b1110 &
b1110 $
#4800
0!
0(
#4900
1!
1(
b1111 &
b1111 $
#5000
0!
0(
#5100
1!
1(
b10000 &
b10000 $
#5200
0!
0(
#5300
1!
1(
b10001 &
b10001 $
#5400
0!
0(
#5500
1!
1(
b10010 &
b10010 $
#5600
0!
0(
#5700
1!
1(
b10011 &
b10011 $
#5800
0!
0(
#5900
1!
1(
b10100 &
b10100 $
#6000
0!
0(
#6100
1!
1(
#6200
0!
0(
#6300
1!
1(
#6400
0!
0(
#6500
1!
1(
#6600
0!
0(
#6700
1!
1(
#6800
0!
0(
#6900
1!
1(
#7000
1#
0!
0(
1%
#7100
1!
1(
b10011 &
b10011 $
#7200
0!
0(
#7300
1!
1(
b10010 &
b10010 $
#7400
0!
0(
#7500
1!
1(
b10001 &
b10001 $
#7600
0!
0(
#7700
1!
1(
b10000 &
b10000 $
#7800
0!
0(
#7900
1!
1(
b1111 &
b1111 $
#8000
0!
0(
#8100
1!
1(
b1110 &
b1110 $
#8200
0!
0(
#8300
1!
1(
b1101 &
b1101 $
#8400
0!
0(
#8500
1!
1(
b1100 &
b1100 $
#8600
0!
0(
#8700
1!
1(
b1011 &
b1011 $
#8800
0!
0(
#8900
1!
1(
b1010 &
b1010 $
#9000
0!
0(
#9100
1!
1(
b1001 &
b1001 $
#9200
0!
0(
#9300
1!
1(
b1000 &
b1000 $
#9400
0!
0(
#9500
1!
1(
b111 &
b111 $
#9600
0!
0(
#9700
1!
1(
b110 &
b110 $
#9800
0!
0(
#9900
1!
1(
b101 &
b101 $
#10000
0!
0(
#10100
1!
1(
b100 &
b100 $
#10200
0!
0(
#10300
1!
1(
b11 &
b11 $
#10400
0!
0(
#10500
1!
1(
b10 &
b10 $
#10600
0!
0(
#10700
1!
1(
b1 &
b1 $
#10800
0!
0(
#10900
1!
1(
b0 &
b0 $
#11000
0!
0(
#11100
1!
1(
#11200
0!
0(
#11300
1!
1(
#11400
0!
0(
#11500
1!
1(
#11600
0!
0(
#11700
1!
1(
#11800
0!
0(
#11900
1!
1(
#12000
0!
0(
#12100
1!
1(
#12200
0!
0(
#12300
1!
1(
#12400
0!
0(
#12500
1!
1(
#12600
0!
0(
#12700
1!
1(
#12800
0!
0(
#12900
1!
1(
#13000
0!
0(
#13100
1!
1(
#13200
0!
0(
#13300
1!
1(
#13400
0!
0(
#13500
1!
1(
#13600
0!
0(
#13700
1!
1(
#13800
0!
0(
#13900
1!
1(
#14000
0!
0(
#14100
1!
1(
#14200
0!
0(
#14300
1!
1(
#14400
0!
0(
#14500
1!
1(
#14600
0!
0(
#14700
1!
1(
#14800
0!
0(
#14900
1!
1(
#15000
0#
0!
0(
0%
#15100
1!
1(
b1 &
b1 $
#15200
0!
0(
#15300
1!
1(
b10 &
b10 $
#15400
0!
0(
#15500
1!
1(
b11 &
b11 $
#15600
0!
0(
#15700
1!
1(
b100 &
b100 $
#15800
0!
0(
#15900
1!
1(
b101 &
b101 $
#16000
0!
0(
#16100
1!
1(
b110 &
b110 $
#16200
0!
0(
#16300
1!
1(
b111 &
b111 $
#16400
0!
0(
#16500
1!
1(
b1000 &
b1000 $
#16600
0!
0(
#16700
1!
1(
b1001 &
b1001 $
#16800
0!
0(
#16900
1!
1(
b1010 &
b1010 $
#17000
0!
0(
#17100
1!
1(
b1011 &
b1011 $
#17200
0!
0(
#17300
1!
1(
b1100 &
b1100 $
#17400
0!
0(
#17500
1!
1(
b1101 &
b1101 $
#17600
0!
0(
#17700
1!
1(
b1110 &
b1110 $
#17800
0!
0(
#17900
1!
1(
b1111 &
b1111 $
#18000
0!
0(
#18100
1!
1(
b10000 &
b10000 $
#18200
0!
0(
#18300
1!
1(
b10001 &
b10001 $
#18400
0!
0(
#18500
1!
1(
b10010 &
b10010 $
#18600
0!
0(
#18700
1!
1(
b10011 &
b10011 $
#18800
0!
0(
#18900
1!
1(
b10100 &
b10100 $
