HW1/E24063058_HW1_v2/Structure/adder_s.v
module FA(SUM, Cout, A, B, Cin);
    input A, B, Cin;
    output SUM, Cout;
    wire w1, w2, w3;
    
    xor xor1(w1, A, B);
    xor xor2(SUM, w1, Cin);
    
    and and1(w2, w1, Cin);
    and and2(w3, A, B);
    
    or or1(Cout, w2, w3);

endmodule
module adder_16bit_s(A , B ,Add_ctrl , O , C_out , SUM);

input [15:00] A , B ;
input Add_ctrl;//1 for SUMub ,0 for add

wire t0, t1, t2, t3, t4,t5,t6,t7,t8,t9,t10,t11,t12,t13,t14,t15;
wire co0, co1, co2, co3, co4,co5,co6,co7,co8,co9,co10,co11,co12,co13,co14;

output [15:0] SUM ;
output C_out ;
output O ;

    xor x0(t0, Add_ctrl, B[0]);
    xor x1(t1, Add_ctrl, B[1]);
    xor x2(t2, Add_ctrl, B[2]);
    xor x3(t3, Add_ctrl, B[3]);
    xor x4(t4, Add_ctrl, B[4]);
    xor x5(t5, Add_ctrl, B[5]);
    xor x6(t6, Add_ctrl, B[6]);
    xor x7(t7, Add_ctrl, B[7]);
    xor x8(t8, Add_ctrl, B[8]);
    xor x9(t9, Add_ctrl, B[9]);
    xor x10(t10, Add_ctrl, B[10]);
    xor x11(t11, Add_ctrl, B[11]);
    xor x12(t12, Add_ctrl, B[12]);
    xor x13(t13, Add_ctrl, B[13]);
    xor x14(t14, Add_ctrl, B[14]);
    xor x15(t15, Add_ctrl, B[15]);

    FA fa0(SUM[0], co0, A[0], t0, Add_ctrl);
    FA fa1(SUM[1], co1, A[1], t1, co0);
    FA fa2(SUM[2], co2, A[2], t2, co1);
    FA fa3(SUM[3], co3, A[3], t3, co2);
    FA fa4(SUM[4], co4, A[4], t4, co3);
    FA fa5(SUM[5], co5, A[5], t5, co4);
    FA fa6(SUM[6], co6, A[6], t6, co5);
    FA fa7(SUM[7], co7, A[7], t7, co6);
    FA fa8(SUM[8], co8, A[8], t8, co7);
    FA fa9(SUM[9], co9, A[9], t9, co8);
    FA fa10(SUM[10], co10, A[10], t10, co9);
    FA fa11(SUM[11], co11, A[11], t11, co10);
    FA fa12(SUM[12], co12, A[12], t12, co11);
    FA fa13(SUM[13], co13, A[13], t13, co12);
    FA fa14(SUM[14], co14, A[14], t14, co13);
    FA fa15(SUM[15], C_out, A[15], t15, co14);

    xor xor_o(O, C_out, co14);

endmodule

HW1/HW1/Structure/testbench.v
`timescale 1ns/10ps
`include        "adder_s.v"

module tb_adder ;
reg [15:0] A , B ;
reg Add_ctrl ;

wire [15:0] SUM;
wire C_out ;
wire O ;


reg [15:0] mem_A [9999:0] ;
reg [15:0] mem_B [9999:0] ;
reg mem_add_ctrl [9999:0] ;
reg [17:0] expect [9999:0] ;

reg    [16:0] error = 0;
integer i ;

initial 
begin
	$readmemh("A.txt", mem_A);
	$readmemh("B.txt", mem_B);
	$readmemh("Add_ctrl.txt", mem_add_ctrl);
	$readmemh("Result.txt", expect);
end


adder_16bit_s u_adder(        .A            (A        ),
                .B            (B        ),
                .Add_ctrl     (Add_ctrl ),
                .O            (O        ),
                .C_out        (C_out    ),
                .SUM          (SUM      )
);

initial 
begin

	for (i =0 ; i <= 9999; i = i + 1 )          
  begin
    A = mem_A[i] ;
	B = mem_B[i] ;
	Add_ctrl = mem_add_ctrl[i] ;
    
    #10;
    if (SUM !== expect[i][15:0])
        begin
           $display ("ERROR at time=%d(pattern%d): SUM(%h)!= expect(%h)",
                      $time, i+1, SUM, expect[i][15:0]);
           error = error + 1;
	end
		
    if (C_out !== expect[i][16])
	begin
           $display ("ERROR at time=%d(pattern%d): C_out(%b)!= expect(%b)", 
                      $time,  i+1, C_out, expect[i][16]);
           error = error + 1;
	end

    if ( O !== expect[i][17])
	begin
           $display ("ERROR at time=%d(pattern%d): O(%b)!= expect(%b)",
                      $time, i+1, O , expect[i][17]);
	    error = error + 1;
	end
    end

     if(error == 17'b0)
     begin
      $display ("=============================================================");
      $display ("Congratulation!, Your design PASSed all the test patterns ");
	  $display ("^     ^");
	  $display (" +++++");
      $display ("=============================================================");
      end
      else
      begin
      $display ("=================================================");
      $display ("There're %d errors in your design", error); 
      $display ("=================================================");
      end

	$finish ;
end


initial
begin
	$dumpfile("adder_s.vcd");
	$dumpvars;
end

	
endmodule

HW1/HW1/Structure/adder_s.vcd
$date
    Oct  8, 2019  20:58:21
$end
$version
    TOOL:	ncsim	15.20-s039
$end
$timescale
    10 ps
$end

$scope module tb_adder $end
$var reg      16 !    A [15:0] $end
$var reg      16 "    B [15:0] $end
$var reg       1 #    Add_ctrl  $end
$var wire      1 $    SUM [15] $end
$var wire      1 %    SUM [14] $end
$var wire      1 &    SUM [13] $end
$var wire      1 '    SUM [12] $end
$var wire      1 (    SUM [11] $end
$var wire      1 )    SUM [10] $end
$var wire      1 *    SUM [9] $end
$var wire      1 +    SUM [8] $end
$var wire      1 ,    SUM [7] $end
$var wire      1 -    SUM [6] $end
$var wire      1 .    SUM [5] $end
$var wire      1 /    SUM [4] $end
$var wire      1 0    SUM [3] $end
$var wire      1 1    SUM [2] $end
$var wire      1 2    SUM [1] $end
$var wire      1 3    SUM [0] $end
$var wire      1 4    C_out  $end
$var wire      1 5    O  $end
$var reg      17 6    error [16:0] $end
$var integer  32 7    i  $end

$scope module u_adder $end
$var wire      1 8    A [15] $end
$var wire      1 9    A [14] $end
$var wire      1 :    A [13] $end
$var wire      1 ;    A [12] $end
$var wire      1 <    A [11] $end
$var wire      1 =    A [10] $end
$var wire      1 >    A [9] $end
$var wire      1 ?    A [8] $end
$var wire      1 @    A [7] $end
$var wire      1 A    A [6] $end
$var wire      1 B    A [5] $end
$var wire      1 C    A [4] $end
$var wire      1 D    A [3] $end
$var wire      1 E    A [2] $end
$var wire      1 F    A [1] $end
$var wire      1 G    A [0] $end
$var wire      1 H    B [15] $end
$var wire      1 I    B [14] $end
$var wire      1 J    B [13] $end
$var wire      1 K    B [12] $end
$var wire      1 L    B [11] $end
$var wire      1 M    B [10] $end
$var wire      1 N    B [9] $end
$var wire      1 O    B [8] $end
$var wire      1 P    B [7] $end
$var wire      1 Q    B [6] $end
$var wire      1 R    B [5] $end
$var wire      1 S    B [4] $end
$var wire      1 T    B [3] $end
$var wire      1 U    B [2] $end
$var wire      1 V    B [1] $end
$var wire      1 W    B [0] $end
$var wire      1 X    Add_ctrl  $end
$var wire      1 Y    t0  $end
$var wire      1 Z    t1  $end
$var wire      1 [    t2  $end
$var wire      1 \    t3  $end
$var wire      1 ]    t4  $end
$var wire      1 ^    t5  $end
$var wire      1 _    t6  $end
$var wire      1 `    t7  $end
$var wire      1 a    t8  $end
$var wire      1 b    t9  $end
$var wire      1 c    t10  $end
$var wire      1 d    t11  $end
$var wire      1 e    t12  $end
$var wire      1 f    t13  $end
$var wire      1 g    t14  $end
$var wire      1 h    t15  $end
$var wire      1 i    co0  $end
$var wire      1 j    co1  $end
$var wire      1 k    co2  $end
$var wire      1 l    co3  $end
$var wire      1 m    co4  $end
$var wire      1 n    co5  $end
$var wire      1 o    co6  $end
$var wire      1 p    co7  $end
$var wire      1 q    co8  $end
$var wire      1 r    co9  $end
$var wire      1 s    co10  $end
$var wire      1 t    co11  $end
$var wire      1 u    co12  $end
$var wire      1 v    co13  $end
$var wire      1 w    co14  $end
$var wire      1 $    SUM [15] $end
$var wire      1 %    SUM [14] $end
$var wire      1 &    SUM [13] $end
$var wire      1 '    SUM [12] $end
$var wire      1 (    SUM [11] $end
$var wire      1 )    SUM [10] $end
$var wire      1 *    SUM [9] $end
$var wire      1 +    SUM [8] $end
$var wire      1 ,    SUM [7] $end
$var wire      1 -    SUM [6] $end
$var wire      1 .    SUM [5] $end
$var wire      1 /    SUM [4] $end
$var wire      1 0    SUM [3] $end
$var wire      1 1    SUM [2] $end
$var wire      1 2    SUM [1] $end
$var wire      1 3    SUM [0] $end
$var wire      1 4    C_out  $end
$var wire      1 5    O  $end

$scope module fa0 $end
$var wire      1 G    A  $end
$var wire      1 Y    B  $end
$var wire      1 X    Cin  $end
$var wire      1 3    SUM  $end
$var wire      1 i    Cout  $end
$var wire      1 x    w1  $end
$var wire      1 y    w2  $end
$var wire      1 z    w3  $end
$upscope $end


$scope module fa1 $end
$var wire      1 F    A  $end
$var wire      1 Z    B  $end
$var wire      1 i    Cin  $end
$var wire      1 2    SUM  $end
$var wire      1 j    Cout  $end
$var wire      1 {    w1  $end
$var wire      1 |    w2  $end
$var wire      1 }    w3  $end
$upscope $end


$scope module fa2 $end
$var wire      1 E    A  $end
$var wire      1 [    B  $end
$var wire      1 j    Cin  $end
$var wire      1 1    SUM  $end
$var wire      1 k    Cout  $end
$var wire      1 ~    w1  $end
$var wire      1 !!   w2  $end
$var wire      1 "!   w3  $end
$upscope $end


$scope module fa3 $end
$var wire      1 D    A  $end
$var wire      1 \    B  $end
$var wire      1 k    Cin  $end
$var wire      1 0    SUM  $end
$var wire      1 l    Cout  $end
$var wire      1 #!   w1  $end
$var wire      1 $!   w2  $end
$var wire      1 %!   w3  $end
$upscope $end


$scope module fa4 $end
$var wire      1 C    A  $end
$var wire      1 ]    B  $end
$var wire      1 l    Cin  $end
$var wire      1 /    SUM  $end
$var wire      1 m    Cout  $end
$var wire      1 &!   w1  $end
$var wire      1 '!   w2  $end
$var wire      1 (!   w3  $end
$upscope $end


$scope module fa5 $end
$var wire      1 B    A  $end
$var wire      1 ^    B  $end
$var wire      1 m    Cin  $end
$var wire      1 .    SUM  $end
$var wire      1 n    Cout  $end
$var wire      1 )!   w1  $end
$var wire      1 *!   w2  $end
$var wire      1 +!   w3  $end
$upscope $end


$scope module fa6 $end
$var wire      1 A    A  $end
$var wire      1 _    B  $end
$var wire      1 n    Cin  $end
$var wire      1 -    SUM  $end
$var wire      1 o    Cout  $end
$var wire      1 ,!   w1  $end
$var wire      1 -!   w2  $end
$var wire      1 .!   w3  $end
$upscope $end


$scope module fa7 $end
$var wire      1 @    A  $end
$var wire      1 `    B  $end
$var wire      1 o    Cin  $end
$var wire      1 ,    SUM  $end
$var wire      1 p    Cout  $end
$var wire      1 /!   w1  $end
$var wire      1 0!   w2  $end
$var wire      1 1!   w3  $end
$upscope $end


$scope module fa8 $end
$var wire      1 ?    A  $end
$var wire      1 a    B  $end
$var wire      1 p    Cin  $end
$var wire      1 +    SUM  $end
$var wire      1 q    Cout  $end
$var wire      1 2!   w1  $end
$var wire      1 3!   w2  $end
$var wire      1 4!   w3  $end
$upscope $end


$scope module fa9 $end
$var wire      1 >    A  $end
$var wire      1 b    B  $end
$var wire      1 q    Cin  $end
$var wire      1 *    SUM  $end
$var wire      1 r    Cout  $end
$var wire      1 5!   w1  $end
$var wire      1 6!   w2  $end
$var wire      1 7!   w3  $end
$upscope $end


$scope module fa10 $end
$var wire      1 =    A  $end
$var wire      1 c    B  $end
$var wire      1 r    Cin  $end
$var wire      1 )    SUM  $end
$var wire      1 s    Cout  $end
$var wire      1 8!   w1  $end
$var wire      1 9!   w2  $end
$var wire      1 :!   w3  $end
$upscope $end


$scope module fa11 $end
$var wire      1 <    A  $end
$var wire      1 d    B  $end
$var wire      1 s    Cin  $end
$var wire      1 (    SUM  $end
$var wire      1 t    Cout  $end
$var wire      1 ;!   w1  $end
$var wire      1 <!   w2  $end
$var wire      1 =!   w3  $end
$upscope $end


$scope module fa12 $end
$var wire      1 ;    A  $end
$var wire      1 e    B  $end
$var wire      1 t    Cin  $end
$var wire      1 '    SUM  $end
$var wire      1 u    Cout  $end
$var wire      1 >!   w1  $end
$var wire      1 ?!   w2  $end
$var wire      1 @!   w3  $end
$upscope $end


$scope module fa13 $end
$var wire      1 :    A  $end
$var wire      1 f    B  $end
$var wire      1 u    Cin  $end
$var wire      1 &    SUM  $end
$var wire      1 v    Cout  $end
$var wire      1 A!   w1  $end
$var wire      1 B!   w2  $end
$var wire      1 C!   w3  $end
$upscope $end


$scope module fa14 $end
$var wire      1 9    A  $end
$var wire      1 g    B  $end
$var wire      1 v    Cin  $end
$var wire      1 %    SUM  $end
$var wire      1 w    Cout  $end
$var wire      1 D!   w1  $end
$var wire      1 E!   w2  $end
$var wire      1 F!   w3  $end
$upscope $end


$scope module fa15 $end
$var wire      1 8    A  $end
$var wire      1 h    B  $end
$var wire      1 w    Cin  $end
$var wire      1 $    SUM  $end
$var wire      1 4    Cout  $end
$var wire      1 G!   w1  $end
$var wire      1 H!   w2  $end
$var wire      1 I!   w3  $end
$upscope $end

$upscope $end

$upscope $end

$enddefinitions $end
$dumpvars
b1111101001011110 !
b1010000110001000 "
0#
1$
0%
0&
1'
1(
0)
1*
1+
1,
1-
1.
0/
00
11
12
03
14
05
b0 6
b0 7
18
19
1:
1;
1<
0=
1>
0?
0@
1A
0B
1C
1D
1E
1F
0G
1H
0I
1J
0K
0L
0M
0N
1O
1P
0Q
0R
0S
1T
0U
0V
0W
0X
0Y
0Z
0[
1\
0]
0^
0_
1`
1a
0b
0c
0d
0e
1f
0g
1h
0i
0j
0k
1l
1m
0n
0o
0p
0q
0r
0s
0t
0u
1v
1w
0x
0y
0z
1{
0|
0}
1~
0!!
0"!
0#!
0$!
1%!
1&!
1'!
0(!
0)!
0*!
0+!
1,!
0-!
0.!
1/!
00!
01!
12!
03!
04!
15!
06!
07!
08!
09!
0:!
1;!
0<!
0=!
1>!
0?!
0@!
0A!
0B!
1C!
1D!
1E!
0F!
0G!
0H!
1I!
$end
#1000
b1 7
b111000111010110 !
b110001011011100 "
1#
1X
0H
1I
1N
0O
1Q
1S
1U
08
0<
0>
1?
1@
0D
0#!
0%!
0l
1/!
01!
0p
02!
14!
1q
05!
1;!
1G!
0I!
1H!
0f
1e
1d
1c
0`
1^
0\
1Z
1Y
03
1x
0{
1}
1j
1)!
0*!
0n
18!
0>!
1@!
1u
1A!
0C!
1B!
0$
0+
1/
0'!
0m
0'
1)
01
1!!
1k
12
1y
1i
10
#2000
b10 7
b110001011111101 !
b1001110010101000 "
0#
0X
1H
0I
0J
1K
1L
1M
0N
0Q
1R
0S
0U
0;
1>
0?
1B
1D
0F
1G
1x
0{
0}
0|
0#!
0$!
1l
0)!
1+!
1n
02!
04!
0q
15!
1>!
0@!
0u
0a
1`
1\
0Z
0Y
0y
0i
0j
1%!
0/!
11!
1p
1&
0B!
0v
1'
1+
0-
1-!
1o
1.
0/
1'!
1m
02
1%
0E!
0w
11
0!!
0k
13
00
05
1$
0H!
04
#3000
b11 7
b1111001111110011 !
b1001010100111100 "
0L
1O
0P
1S
1U
18
1;
1?
0D
0E
1F
1{
1~
1#!
0%!
0l
02!
03!
1q
0>!
1@!
1u
0G!
1I!
14
1[
1]
0`
1a
0d
0;!
14!
1/!
01!
10!
0&!
05
1$
0&
1B!
1v
0'
0*
16!
1r
1(!
0'!
10
12
0)
19!
1s
0%
1E!
1w
0,
#4000
b100 7
b1001111111111110 !
b1101001101011011 "
1#
1X
1I
0M
1N
1Q
0R
0U
1V
1W
09
0:
1<
1=
1D
1E
0G
0x
0~
1"!
1k
1#!
0%!
1l
08!
1:!
09!
0;!
0<!
1t
1A!
1B!
1v
0D!
0E!
0w
0h
1f
0e
1d
0a
1`
0]
0\
1$!
1&!
0/!
11!
00!
12!
04!
13!
1=!
1>!
1G!
05
0I!
04
1%
0@!
1?!
1)
0(!
1'!
00
01
0+
1,
#5000
b101 7
b1001001101000100 !
b101111000011000 "
0#
0X
0H
1L
1M
0O
0Q
0V
0W
0<
0=
0@
0B
0C
0D
0F
0{
1#!
0$!
0l
1&!
0'!
0m
0)!
0+!
0n
0/!
01!
00!
18!
0:!
19!
1;!
0=!
1<!
1g
0f
1e
1b
0`
0^
1]
1\
0[
03
1~
0"!
0k
0p
05!
17!
06!
0>!
1@!
0?!
0A!
0B!
0v
1D!
0(
0)
1-
0-!
0o
0.
1/
10
02
0,
1&
1'
0*
1+
03!
0q
11
#6000
b110 7
b11001010110 !
b11000101011 "
1#
1X
0I
0K
0L
1R
0S
1V
1W
08
0;
1=
0?
1C
1F
1{
0&!
1(!
1m
12!
18!
0:!
19!
1>!
0@!
1?!
1G!
1h
1f
0c
0b
1a
1`
1_
0\
1[
13
0~
1"!
1k
0#!
0,!
1.!
1o
1/!
10!
1p
13!
1q
15!
07!
16!
1A!
1B!
1v
0'
0+
1.
0/
12
0%
1E!
1w
0&
0-
01
05
0$
1H!
14
#7000
b111 7
b11010000111 !
b110001101000000 "
1I
1J
0M
1O
1Q
0R
0T
0V
0W
1@
0A
0C
1G
0x
0y
1i
1&!
0(!
1m
0,!
0.!
0o
0/!
11!
00!
1Y
1Z
1\
1^
0_
0a
1c
0f
0g
0D!
0E!
0w
0A!
0B!
0v
08!
1:!
09!
02!
03!
0q
1)!
1#!
1$!
1l
0{
1z
1}
1j
11
1'!
00
1*
06!
0r
1+
1&
05
1$
0H!
04
0.
1*!
1n
1-
#8000
b1000 7
b100011000010110 !
b101110100101110 "
0J
1K
1L
1M
0N
0Q
1R
1T
1U
1V
19
0@
1C
0G
1x
0z
1y
0&!
1(!
0'!
1/!
01!
0p
1D!
0Z
0[
0\
0^
1_
1b
0c
0d
0e
1f
1A!
0B!
0v
0>!
0?!
0u
0;!
0<!
0t
18!
0:!
1s
05!
17!
1r
1,!
0-!
0o
0)!
0*!
0n
0#!
0$!
0l
1~
0"!
1!!
1{
0}
1|
0+
03
02
01
10
1.
19!
0*
1(
1%
1,
#9000
b1001 7
b1101011101010100 !
b10010011111101 "
0#
0X
0I
1J
0K
0L
0O
1P
1Q
1S
0V
1W
18
1;
1?
1A
0F
0{
0|
0j
0,!
1.!
1o
12!
1>!
1G!
0I!
04
0h
1c
0b
1^
1\
1[
13
0y
0i
0~
1#!
1$!
1l
1)!
1*!
1n
15!
07!
1r
08!
1:!
09!
1'
0+
0,
10!
1p
1"!
0!!
13!
1q
0.
1/
00
16!
1)
#10000
b1010 7
b1101010111101001 !
b100100001101011 "
1I
0J
1L
0M
0P
0S
0U
1V
0>
1@
1B
0C
1D
0E
1G
0x
1z
1i
0~
0"!
0k
0#!
1%!
0$!
0&!
0(!
0'!
0)!
1+!
0*!
1/!
01!
10!
05!
06!
0r
1Z
0[
0]
0`
0c
1d
0f
1g
0D!
1F!
1w
0A!
1;!
0<!
0t
18!
0m
1{
0:!
0s
1*
1|
1j
03
11
0&
05
0$
1H!
14
0%
#11000
b1011 7
b110001000011010 !
b1111001011010001 "
1H
1J
1K
0L
1N
1P
0R
1S
0T
0V
08
1:
0;
0=
1>
0?
0@
0A
0B
1C
1F
0G
1x
0z
0i
1{
0}
0|
0&!
0'!
1m
0)!
0+!
0*!
1,!
0.!
0-!
1/!
00!
0p
02!
03!
0q
05!
08!
1>!
0A!
1G!
1H!
14
0Z
0\
1]
0^
1`
1b
0d
1e
1f
1h
1C!
1v
0;!
17!
1r
0n
1(!
1#!
0%!
0l
0j
0*
0+
1.
0/
12
13
01
10
0o
0(
1%
1,
#12000
b1100 7
b11010011111 !
b1100110111101100 "
1#
1X
0J
0K
1L
1M
0N
1O
1R
0S
1T
1U
0W
09
0:
1=
1@
1E
1G
0x
1~
1/!
01!
0p
18!
19!
1s
1A!
0C!
0v
0D!
0F!
0w
0h
0g
0`
0_
1Z
1z
1i
12
0{
1}
1j
0,!
0G!
05
0H!
04
0%
1&
1(
0)
0-
1!!
1k
00
1$!
1l
1/
#13000
b1101 7
b1000100101000 !
b1100011111011011 "
0L
1N
0R
1S
0U
1V
1W
1;
0=
0>
1?
0@
1B
0C
0E
0F
0G
0x
0z
0y
0{
0}
0|
1~
0!!
0k
0&!
0(!
0'!
0)!
0*!
1n
0/!
12!
05!
07!
0r
08!
09!
0s
0>!
1@!
1u
0Y
0Z
1[
0]
1^
0b
1d
1;!
1+!
0m
0j
0i
0&
1B!
1v
0'
1+
0,
1-
0.
11
02
1%
10
0$!
0l
0/
#14000
b1110 7
b101110111100101 !
b1110101110000 "
0#
0X
0H
0I
1K
1L
0N
0P
1R
0T
0V
0W
19
1<
1=
1@
1A
0D
1E
1G
1x
1~
0"!
0k
0#!
0,!
0-!
1o
1/!
10!
1p
08!
0;!
1=!
1t
1D!
0E!
0w
0f
1c
1a
1_
1]
0[
1&!
1.!
02!
1:!
1s
0A!
0B!
0v
05
0$
1'
14!
1q
00
1*
1&
1/
#15000
b1111 7
b10111000 !
b10100100100111 "
1J
0K
0M
0Q
0S
1U
1V
1W
09
0;
0<
0=
0?
0A
1C
1D
0E
0G
1x
1~
1#!
1&!
0(!
0m
0,!
0.!
0-!
12!
04!
03!
08!
0:!
0s
1;!
0=!
0t
0>!
0@!
0u
0D!
1Y
1Z
1[
0]
0_
0c
0e
1f
1A!
0o
1{
0%
0'
1+
10
12
1,
00!
0p
0q
0*
#16000
b10000 7
b100001111001011 !
b1010111100001110 "
1H
1M
1N
0R
1T
0W
19
1>
1?
1A
0B
0C
1F
1G
1x
0z
0i
0{
1}
1j
0&!
0)!
0+!
0n
1,!
02!
14!
1q
05!
06!
1r
1D!
0Y
1\
0^
1b
1c
1h
1G!
18!
17!
0#!
1%!
1l
1%
19!
1s
1*
0+
01
1!!
1k
02
0(
1<!
1t
1$
1'
#17000
b10001 7
b100110111 !
b1011110111011010 "
1#
1X
1K
0N
1P
1Q
1S
0U
09
0>
0@
0A
1B
1C
0D
1E
0~
1"!
0!!
0#!
0%!
0$!
1&!
0'!
0m
0)!
0*!
1n
0,!
0/!
15!
07!
06!
1D!
0h
1g
0f
0d
0c
0a
1^
0\
0Z
1Y
13
1z
0y
1i
02
0x
1{
0}
1|
0l
1+!
12!
04!
0q
08!
09!
0s
0;!
0<!
0t
0A!
0G!
0,
0.
11
0$
0&
0'
0)
0r
1+
#18000
b10010 7
b1100111001010011 !
b110010101001011 "
0#
0X
0H
1I
0K
0L
0P
0S
1W
18
19
1<
1=
1>
0?
1A
0B
0E
0~
0"!
0!!
0)!
0+!
0n
0,!
12!
15!
07!
0r
08!
09!
1s
1;!
1<!
1t
0D!
1F!
1w
1G!
1H!
14
1f
1c
0b
1a
1_
0^
1\
0[
1Z
03
0{
1}
0|
0k
1#!
1.!
1o
1:!
1A!
0%
1'
0-
1&
1,
12
#19000
b10011 7
b1010001010101001 !
b111010101111 "
1#
1X
0I
0J
1L
1N
0O
1P
0Q
1R
1U
09
1:
0<
0=
1@
0A
1B
0C
1D
0F
0{
0}
0|
1#!
0%!
0l
1&!
1)!
1,!
0.!
0o
1/!
08!
0:!
0s
0;!
0<!
0t
0A!
1C!
1v
1D!
0F!
1E!
1h
1e
0c
1]
0\
0Z
0Y
03
0z
1i
1x
0j
1>!
0G!
1I!
0H!
0&
1-
1.
12
1$
01
1y
#20000
b10100 7
b1011001010100011 !
b1010111100010101 "
0#
0X
1H
1J
1O
0P
0R
1S
0T
0V
1;
0D
1F
1{
1|
1j
0#!
1>!
0@!
1u
0g
0e
1d
1c
1b
0_
1[
1Y
03
1z
0y
0x
1~
0,!
05!
17!
1r
18!
19!
1s
1;!
1<!
1t
1?!
0D!
0E!
0w
1&
0'
10
1!!
1k
02
15
0$
1%
0*
0-
#21000
b10101 7
b1010111100000101 !
b1111000011001000 "
1#
1X
1I
1K
0L
0M
0N
0O
1P
1Q
0S
1T
0U
0W
0;
1<
1=
1?
0@
0B
1E
0F
1{
1|
1j
0~
1"!
0!!
1)!
0/!
02!
14!
1q
08!
1:!
09!
0;!
1=!
0<!
0>!
0?!
0u
0h
0f
1^
1Z
13
1A!
1G!
0I!
04
0C!
0v
1'
1(
1)
1*
0+
0,
11
0%
05
1$
#22000
b10110 7
b1010100111101100 !
b1111011111001011 "
0#
0X
1M
1N
1O
1V
1W
0=
0>
1@
1A
1B
1D
0G
1x
0#!
0$!
1l
1)!
0+!
0n
0,!
0-!
1o
0/!
00!
1p
15!
07!
16!
18!
0:!
19!
1h
1g
1f
1e
0d
1`
1_
0^
0]
1\
0[
0z
0i
12
0|
0j
1~
0"!
0k
1%!
0&!
1.!
11!
1;!
0=!
1<!
1>!
1?!
1u
0A!
1C!
1v
1D!
1E!
1w
0G!
1I!
14
0)
0*
1+
1,
00
0'
0(
#23000
b10111 7
b1111100111111101 !
b1100010011111101 "
1#
1X
0J
0K
0N
0O
1R
1S
1U
0V
19
1;
1C
1G
1x
1&!
1'!
1m
0>!
1@!
0?!
1D!
0F!
1E!
0h
0g
1d
0c
0`
0_
0\
0Y
1#!
0%!
1l
1,!
0.!
1o
1/!
01!
1p
08!
09!
0s
0;!
1=!
0<!
1G!
0I!
1H!
1'
0.
1*!
1n
1-!
0$
1)
1+
0,
00
03
1y
1i
02
1|
1j
10!
0-
01
1!!
1k
1$!
0/
#24000
b11000 7
b1000000000001111 !
b1010010100011011 "
0I
1J
1O
0P
0Q
0R
0U
1V
09
0:
0;
0<
0?
0@
0A
0B
0C
1F
1{
0}
1|
0&!
0'!
0m
1)!
0*!
0n
1,!
0-!
0o
1/!
00!
0p
02!
04!
0q
1;!
0=!
0t
1>!
0@!
0u
0A!
0C!
0v
1D!
0E!
0w
0Z
1[
1^
1_
1`
0a
0f
1g
0~
1"!
0!!
05
1$
0H!
04
1%
0&
1(
1*
06!
0r
0+
1,
1-
1.
1/
0)
11
#25000
b11001 7
b1111011110010011 !
b110000010011001 "
0H
1I
0M
0O
1P
0V
19
1:
1;
1=
1>
1?
1@
1C
0D
0E
1~
0"!
1!!
0#!
0$!
0l
1&!
1/!
01!
0p
02!
03!
1q
05!
17!
1r
08!
09!
1s
0>!
1@!
1u
1A!
1B!
1v
1D!
0F!
1w
1Z
0`
1a
1c
0g
1h
0G!
1E!
1:!
14!
0{
1}
0|
05
1I!
14
0%
1'
0(
1<!
1t
1)
10
01
12
#26000
b11010 7
b100100110110011 !
b1110010011011110 "
1H
1M
1Q
1U
1V
0W
08
0:
0;
1<
0=
0>
1B
0)!
1+!
1n
15!
07!
16!
08!
0:!
09!
0;!
1=!
0<!
1>!
0@!
1?!
0A!
0B!
0v
0G!
0I!
0H!
1Y
0Z
0[
0_
0c
0h
04
0s
0,!
0~
0!!
0k
1{
0}
1|
0x
1z
0y
1%
0E!
0w
1&
0'
0*
0.
0$
13
02
00
11
#27000
b11011 7
b111001110100010 !
b1000011111001111 "
0I
0J
1N
1O
0S
1W
1:
1;
0<
1>
0C
0G
0x
0z
0y
1&!
15!
07!
06!
1;!
0=!
0t
0>!
1@!
0?!
0A!
0B!
1v
0Y
1]
0a
0b
1f
1g
0D!
1C!
12!
04!
0q
0i
1F!
1w
1(
1*
15
1$
12
0|
0j
0r
1+
0)
01
#28000
b11100 7
b10011111011100 !
b111001001111101 "
0#
0X
0H
1I
1J
1K
0M
0O
0P
1R
1S
0V
09
0;
1=
1A
0B
1C
1D
1E
0F
0{
0~
0#!
0&!
1(!
1m
1)!
0+!
1*!
0,!
0-!
1o
18!
1>!
0@!
0u
1D!
0F!
1E!
0d
1b
1_
1\
1[
1Y
13
1x
1"!
1k
1%!
1l
1.!
05!
17!
1r
0;!
0%
0&
1'
0,
10!
1p
10
02
0+
13!
1q
1(
19!
1s
#29000
b11101 7
b101110001010000 !
b1000111000100 "
0I
0J
0N
1O
1P
0R
0S
0T
0W
19
0:
1;
1<
0>
0?
0@
0D
0E
1~
0"!
0k
0#!
0%!
0l
1/!
10!
1p
12!
13!
1q
05!
07!
0r
1;!
0<!
0t
0>!
1@!
1u
0A!
0C!
0B!
1D!
0F!
0E!
0Y
0\
0]
0^
1`
1a
0b
0f
0g
0v
0)!
0*!
0n
1&!
0x
1%
1&
1(
1)
09!
0s
1*
0(!
0m
00
11
03
0-
0w
05
0$
0'
#30000
b11110 7
b111000011111000 !
b1000110000111110 "
1#
1X
1H
0K
1L
1M
0O
0P
0Q
1R
1S
1T
1V
1:
0<
0=
1@
1B
1D
1#!
1)!
0/!
11!
00!
08!
0;!
0A!
0B!
1v
1g
1f
1b
0[
1Y
03
1x
0~
15!
16!
1r
1C!
0D!
1F!
1w
0(
1,
1.
10
15
1$
0*
01
1y
1i
12
#31000
b11111 7
b1001001101101110 !
b111001000110111 "
0#
0X
0H
1I
1J
1K
0L
0M
1N
0T
1W
18
09
0:
1>
1?
0@
0C
1E
1F
0{
0|
1j
0~
0!!
1k
1&!
0/!
01!
00!
12!
04!
03!
05!
17!
06!
1A!
0C!
1B!
1D!
0F!
1E!
1G!
1H!
14
0a
0`
0_
1^
1]
1[
1Z
13
0y
0i
1}
1"!
0)!
1+!
1n
1,!
0.!
1-!
0p
0q
05
0$
0%
0&
1+
00
1$!
1l
11
02
0/
1'!
1m
#32000
b100000 7
b1111100010111110 !
b101001111001001 "
1#
1X
0J
1O
1P
1Q
0R
0S
1T
0U
0V
19
1:
1<
0>
0?
1@
0A
1C
0&!
1(!
0'!
0,!
0-!
0o
1/!
02!
05!
07!
0r
0;!
0A!
1C!
0B!
1D!
0F!
1E!
1h
0g
0e
1d
1c
0b
0Y
13
0y
0i
02
0x
18!
1=!
1t
1>!
0@!
1?!
0G!
1I!
0H!
1&
0+
1-
1/
1$
#33000
b100001 7
b110000001000001 !
b1000010111001010 "
0#
0X
1H
0I
0K
1M
0N
1V
0W
08
0;
0<
0@
1A
0B
0C
0D
0E
0F
1G
1x
1{
0}
0j
0~
0"!
0k
1#!
0$!
0l
0&!
0(!
0m
0)!
0+!
0n
0,!
1/!
0;!
0=!
0t
0>!
0?!
0u
1G!
0I!
0H!
0f
0d
1a
1`
1_
0^
0]
1\
0[
1.!
1o
10!
1p
12!
13!
1q
1A!
1$
0C!
0v
0,
0-
0.
0/
10
01
12
1%
0E!
0w
1*
05
04
